{"main_language": "shell script", "ohloh_name": "onetime", "max_month": "2014-03-01T00:00:00Z", "description": "[1TY](https://1ty.me/) is \"One Time Self Destructing Links For Sharing Sensitive Information\"", "tags": [], "ohloh_analysis": "19399016", "total_code_lines": "2886", "ohloh_description": "Encoder/decoder for one-time pad encryption.  Uses a command-line interface, and has basic pad-management fetaures, including remembering previously-used pad ranges.", "updated_at": "2014-03-15T19:02:57Z", "min_month": "2004-10-01T00:00:00Z", "total_commit_count": "578", "ohloh_id": "480313", "name": "OneTime (1ty)", "total_contributor_count": "3", "twelve_month_contributor_count": "2", "factoids": ["Mature, well-established codebase", "Increasing Y-O-Y development activity", "Well-commented source code", "Small development team"], "twelve_month_commit_count": "274"}